ai_sprint/__init__.py
ai_sprint/cli.py
ai_sprint-0.0.1.dist-info/METADATA
ai_sprint-0.0.1.dist-info/WHEEL
ai_sprint-0.0.1.dist-info/entry_points.txt
ai_sprint-0.0.1.dist-info/RECORD
