Metadata-Version: 2.4
Name: ai-sprint
Version: 0.0.1
Summary: CLI for managing development sprints and .sprint directory structures.
Author-email: Ibrahim Olanigan <ibrahim.olanigan@gmail.com>
Requires-Python: >=3.11
Requires-Dist: click>=8.0.0
Requires-Dist: python-frontmatter>=1.0.0
Requires-Dist: rich>=13.0.0
